beekeeper_sdk/VERSION
beekeeper_sdk/__init__.py
beekeeper_sdk/beekeeper_sdk.py
beekeeper_sdk/client.py
beekeeper_sdk/exceptions.py
beekeeper_sdk/iterators.py
beekeeper_sdk/conversations/__init__.py
beekeeper_sdk/conversations/conversations.py
beekeeper_sdk/files/__init__.py
beekeeper_sdk/files/files.py
beekeeper_sdk/profiles/__init__.py
beekeeper_sdk/profiles/profiles.py
beekeeper_sdk/status/__init__.py
beekeeper_sdk/status/status.py
beekeeper_sdk/streams/__init__.py
beekeeper_sdk/streams/streams.py
beekeeper_sdk/users/__init__.py
beekeeper_sdk/users/users.py
beekeeper_sdk-0.3.4.dist-info/LICENSE
beekeeper_sdk-0.3.4.dist-info/METADATA
beekeeper_sdk-0.3.4.dist-info/WHEEL
beekeeper_sdk-0.3.4.dist-info/top_level.txt
beekeeper_sdk-0.3.4.dist-info/RECORD
